anduril/__init__.py
anduril/client.py
anduril/core/__init__.py
anduril/core/api_error.py
anduril/core/client_wrapper.py
anduril/core/custom_pagination.py
anduril/core/datetime_utils.py
anduril/core/file.py
anduril/core/force_multipart.py
anduril/core/http_client.py
anduril/core/http_response.py
anduril/core/http_sse/__init__.py
anduril/core/http_sse/_api.py
anduril/core/http_sse/_decoders.py
anduril/core/http_sse/_exceptions.py
anduril/core/http_sse/_models.py
anduril/core/jsonable_encoder.py
anduril/core/pagination.py
anduril/core/pydantic_utilities.py
anduril/core/query_encoder.py
anduril/core/remove_none_from_dict.py
anduril/core/request_options.py
anduril/core/serialization.py
anduril/entities/__init__.py
anduril/entities/client.py
anduril/entities/raw_client.py
anduril/entities/types/__init__.py
anduril/entities/types/stream_entities_response.py
anduril/entity/__init__.py
anduril/entity/types/__init__.py
anduril/entity/types/error.py
anduril/environment.py
anduril/errors/__init__.py
anduril/errors/bad_request_error.py
anduril/errors/content_too_large_error.py
anduril/errors/insufficient_storage_error.py
anduril/errors/internal_server_error.py
anduril/errors/not_found_error.py
anduril/errors/request_timeout_error.py
anduril/errors/too_many_requests_error.py
anduril/errors/unauthorized_error.py
anduril/object/__init__.py
anduril/object/types/__init__.py
anduril/object/types/error.py
anduril/objects/__init__.py
anduril/objects/client.py
anduril/objects/raw_client.py
anduril/objects/types/__init__.py
anduril/objects/types/get_object_request_accept_encoding.py
anduril/py.typed
anduril/task/__init__.py
anduril/task/types/__init__.py
anduril/task/types/error.py
anduril/tasks/__init__.py
anduril/tasks/client.py
anduril/tasks/raw_client.py
anduril/tasks/types/__init__.py
anduril/tasks/types/task_query_status_filter.py
anduril/tasks/types/task_query_status_filter_status.py
anduril/tasks/types/task_query_update_time_range.py
anduril/types/__init__.py
anduril_lattice_sdk-4.0.0.dist-info/LICENSE
anduril_lattice_sdk-4.0.0.dist-info/METADATA
anduril_lattice_sdk-4.0.0.dist-info/WHEEL
anduril_lattice_sdk-4.0.0.dist-info/RECORD
